setup.py
bread/dl/__init__.py
bread/dl/activations.py
bread/dl/initializations.py
bread/dl/model.py
bread/dl/objectives.py
bread/dl/optimizers.py
bread/dl/layers/__init__.py
bread/dl/layers/base.py
bread/dl/layers/convolution.py
bread/dl/layers/core.py
bread/dl/layers/embedding.py
bread/dl/layers/normalization.py
bread/dl/layers/pooling.py
bread/dl/layers/recurrent.py
bread/dl/layers/shape.py
bread/dl/utils/__init__.py
bread/dl/utils/data.py
bread/dl/utils/random.py
bread_dl.egg-info/PKG-INFO
bread_dl.egg-info/SOURCES.txt
bread_dl.egg-info/dependency_links.txt
bread_dl.egg-info/top_level.txt