Metadata-Version: 1.1
Name: bread-dl
Version: 0.0.1
Summary: Basic processing tools in common algorithms.
Home-page: https://github.com/Joe-Laue/bread-dl
Author: Joe
Author-email: joe.laue@outlook.com
License: MIT
Platform: UNKNOWN
Classifier: Development Status :: 2 - Pre-Alpha
Classifier: Intended Audience :: Developers
Classifier: Topic :: Scientific/Engineering
Classifier: License :: OSI Approved :: MIT License
Classifier: Programming Language :: Python :: 3.7
Classifier: Programming Language :: Python :: 3.8
